yohtml/HTPY.py
yohtml/__init__.py
YoHtml-0.3.dist-info/LICENSE
YoHtml-0.3.dist-info/METADATA
YoHtml-0.3.dist-info/WHEEL
YoHtml-0.3.dist-info/top_level.txt
YoHtml-0.3.dist-info/RECORD
