Metadata-Version: 2.1
Name: YoHtml
Version: 0.3
Summary: This allows you to create HTML websites in Python language
Home-page: https://github.com/weee456/PyHtml-yobi
Author: weee456
Author-email: jhweee456@outlook.com
License: MIT
Platform: UNKNOWN
Classifier: Programming Language :: Python :: 3
Classifier: License :: OSI Approved :: MIT License
Classifier: Operating System :: OS Independent
License-File: LICENSE
